inpop/__init__.py
inpop/cnumba.py
inpop/constants.py
inpop/inpop.ini
inpop/inpop.py
inpop-0.5.4.dist-info/METADATA
inpop-0.5.4.dist-info/WHEEL
inpop-0.5.4.dist-info/licenses/LICENSE
inpop-0.5.4.dist-info/RECORD
